sinapsis_docling/helpers/__init__.py
sinapsis_docling/helpers/docling_config.py
sinapsis_docling/helpers/docling_utils.py
sinapsis_docling/templates/__init__.py
sinapsis_docling/templates/docling_custom_conversion.py
sinapsis_docling/templates/docling_simple_conversion.py
sinapsis_docling-0.1.6.dist-info/licenses/LICENSE
sinapsis_docling-0.1.6.dist-info/METADATA
sinapsis_docling-0.1.6.dist-info/WHEEL
sinapsis_docling-0.1.6.dist-info/top_level.txt
sinapsis_docling-0.1.6.dist-info/RECORD
