Metadata-Version: 2.4
Name: sinapsis-docling
Version: 0.1.6
Summary: Package to perform document conversion using Docling
Author-email: SinapsisAI <dev@sinapsis.tech>
Project-URL: Homepage, https://sinapsis.tech
Project-URL: Documentation, https://docs.sinapsis.tech/docs
Project-URL: Tutorials, https://docs.sinapsis.tech/tutorials
Project-URL: Repository, https://github.com/Sinapsis-AI/sinapsis-docling.git
Requires-Python: >=3.10
License-File: LICENSE
Requires-Dist: docling>=2.28.4
Requires-Dist: sinapsis>=0.2.1
Dynamic: license-file
